LICENSE
README.md
pyproject.toml
setup.cfg
setup.py
libraspike_art_python/__init__.py
libraspike_art_python/ffi_build.py
libraspike_art_python/version.py
libraspike_art_python.egg-info/PKG-INFO
libraspike_art_python.egg-info/SOURCES.txt
libraspike_art_python.egg-info/dependency_links.txt
libraspike_art_python.egg-info/requires.txt
libraspike_art_python.egg-info/top_level.txt