Metadata-Version: 2.1
Name: libraspike-art-python
Version: 0.0.3
Summary: Python CFFI Bindings for libraspike-art
Author: Wataru Taniguchi
Author-email: wataru@taniguchifamily.com
License: MIT
Classifier: Programming Language :: Python :: 3
Classifier: Programming Language :: Python :: Implementation :: CPython
Classifier: Programming Language :: Python :: Implementation :: PyPy
License-File: LICENSE
